{
  "python_version": "3.10.19 (main, Oct  9 2025, 15:25:03) [Clang 17.0.0 (clang-1700.3.19.1)]",
  "python_executable": "/opt/homebrew/opt/python@3.10/bin/python3.10",
  "platform_system": "Darwin",
  "platform_release": "25.4.0",
  "proc_rss_mb": 16.671875,
  "available_mem_mb": 1761361920.0,
  "swap_used_mb": 11734.0,
  "swap_total_mb": 13312.0,
  "swap_free_mb": 1578.0,
  "swap_detected": true,
  "lancedb_version": null,
  "lancedb_import_error": "No module named 'lancedb'",
  "pyarrow_version": "21.0.0",
  "fastmcp_available": false,
  "fastmcp_version": null,
  "fastembed_available": false,
  "fastembed_version": null,
  "mlx_available": true,
  "mlx_version": "0.30.1",
  "sentence_transformers_available": false,
  "heavy_imports_avoided": true,
  "checked_by_spec": [
    "fastembed",
    "sentence_transformers"
  ],
  "chromadb_in_modules": false,
  "default_backend": "lance",
  "palace_path": "/var/folders/wx/6pbc46rn1w57p4w4v2zbcgb40000gn/T/mempalace_session_jw7udnk1/.mempalace/palace",
  "collection_name": "mempalace_drawers",
  "lance_collection_count": null,
  "fts5_count": null,
  "symbol_index_stats": null
}